{
    "path0": {
        "page0": {
            "style": {
                "backgroundImage": "url(img/path0_page0.jpg)",
                "backgroundColor": "#812625"
            },
            "neighbours": [
                {
                    "pathIndex": 0,
                    "pageIndex": 1,
                    "style": {
                        "width": "400px",
                        "height": "150px",
                        "top": "70%",
                        "left": "0",
                        "right": "0",
                        "margin": "auto"
                    },
                    "imgSrc": "img/path0_page0_btn0.png"
                }
            ]
        },
        "page1": {
            "style": {
                "backgroundImage": "url(img/test1.jpg)",
                "backgroundColor": "#812625"
            },
            "neighbours": [
                {
                    "pathIndex": 0,
                    "pageIndex": 0,
                    "style": {
                        "width": "400px",
                        "height": "150px",
                        "top": "20%",
                        "right": "50px"
                    },
                    "imgSrc": "img/path0_page0_btn0.png"
                }
            ]
        }
    }
}
